{
  "kind": "singleType",
  "collectionName": "landing_pages",
  "info": {
    "name": "landingPage",
    "description": ""
  },
  "options": {
    "increments": true,
    "timestamps": true,
    "draftAndPublish": true
  },
  "attributes": {
    "title": {
      "type": "string",
      "unique": true
    },
    "characters": {
      "collection": "character"
    },
    "image": {
      "model": "file",
      "via": "related",
      "allowedTypes": [
        "images"
      ],
      "plugin": "upload",
      "required": true
    },
    "description": {
      "type": "text",
      "required": true
    }
  }
}
